iofstream/__init__.py
iofstream/file_functions.py
iofstream/log.py
iofstream/testing.py
iofstream/testing2.py
iofstream-0.1.0.dist-info/METADATA
iofstream-0.1.0.dist-info/WHEEL
iofstream-0.1.0.dist-info/top_level.txt
iofstream-0.1.0.dist-info/RECORD
