Metadata-Version: 2.1
Name: iofstream
Version: 0.1.0
Summary: Input/Output File Stream
Home-page: UNKNOWN
Author: ST
Author-email: arrowsoul@protonmail.com
License: UNKNOWN
Keywords: python,input,output,file,stream,handling
Platform: UNKNOWN
Classifier: Development Status :: 1 - Planning
Classifier: Intended Audience :: Developers
Classifier: Programming Language :: Python :: 3
Classifier: Operating System :: Unix
Classifier: Operating System :: MacOS :: MacOS X
Classifier: Operating System :: Microsoft :: Windows
Requires-Dist: colorama
Requires-Dist: sty
